[
  {
    "month": 10,
    "year": 2015,
    "rankings": [
      {
        "team": "UTA",
        "rank": 1,
        "stat": 86.6
      },
      {
        "team": "DEN",
        "rank": 2,
        "stat": 91.8
      },
      {
        "team": "CLE",
        "rank": 3,
        "stat": 92.3
      },
      {
        "team": "DET",
        "rank": 4,
        "stat": 92.9
      },
      {
        "team": "PHX",
        "rank": 5,
        "stat": 94.8
      },
      {
        "team": "SAS",
        "rank": 6,
        "stat": 94.9
      },
      {
        "team": "TOR",
        "rank": 7,
        "stat": 95.3
      },
      {
        "team": "CHI",
        "rank": 8,
        "stat": 95.4
      },
      {
        "team": "MIN",
        "rank": 9,
        "stat": 95.5
      },
      {
        "team": "LAC",
        "rank": 10,
        "stat": 97.4
      },
      {
        "team": "DAL",
        "rank": 11,
        "stat": 97.5
      },
      {
        "team": "BOS",
        "rank": 12,
        "stat": 98.1
      },
      {
        "team": "GSW",
        "rank": 13,
        "stat": 99.4
      },
      {
        "team": "POR",
        "rank": 14,
        "stat": 99.7
      },
      {
        "team": "ATL",
        "rank": 15,
        "stat": 100.3
      },
      {
        "team": "ORL",
        "rank": 16,
        "stat": 101.3
      },
      {
        "team": "WAS",
        "rank": 17,
        "stat": 103.3
      },
      {
        "team": "NYK",
        "rank": 18,
        "stat": 103.9
      },
      {
        "team": "CHA",
        "rank": 19,
        "stat": 104.1
      },
      {
        "team": "MEM",
        "rank": 20,
        "stat": 105.3
      },
      {
        "team": "MIA",
        "rank": 21,
        "stat": 105.4
      },
      {
        "team": "SAC",
        "rank": 22,
        "stat": 106.3
      },
      {
        "team": "OKC",
        "rank": 23,
        "stat": 106.6
      },
      {
        "team": "IND",
        "rank": 24,
        "stat": 107.1
      },
      {
        "team": "HOU",
        "rank": 25,
        "stat": 108.5
      },
      {
        "team": "PHI",
        "rank": 26,
        "stat": 109.3
      },
      {
        "team": "BKN",
        "rank": 27,
        "stat": 110.4
      },
      {
        "team": "NOP",
        "rank": 28,
        "stat": 115.2
      },
      {
        "team": "LAL",
        "rank": 29,
        "stat": 117.9
      },
      {
        "team": "MIL",
        "rank": 30,
        "stat": 121.2
      }
    ]
  },
  {
    "month": 11,
    "year": 2015,
    "rankings": [
      {
        "team": "SAS",
        "rank": 1,
        "stat": 94.3
      },
      {
        "team": "IND",
        "rank": 2,
        "stat": 95.1
      },
      {
        "team": "MIA",
        "rank": 3,
        "stat": 97
      },
      {
        "team": "BOS",
        "rank": 4,
        "stat": 98
      },
      {
        "team": "CHI",
        "rank": 5,
        "stat": 99.5
      },
      {
        "team": "GSW",
        "rank": 6,
        "stat": 99.6
      },
      {
        "team": "CHA",
        "rank": 7,
        "stat": 100.8
      },
      {
        "team": "ORL",
        "rank": 8,
        "stat": 101.4
      },
      {
        "team": "DET",
        "rank": 9,
        "stat": 101.9
      },
      {
        "team": "DAL",
        "rank": 10,
        "stat": 102
      },
      {
        "team": "TOR",
        "rank": 11,
        "stat": 102.3
      },
      {
        "team": "OKC",
        "rank": 12,
        "stat": 102.5
      },
      {
        "team": "BKN",
        "rank": 13,
        "stat": 103.3
      },
      {
        "team": "ATL",
        "rank": 14,
        "stat": 103.4
      },
      {
        "team": "MEM",
        "rank": 15,
        "stat": 103.4
      },
      {
        "team": "MIN",
        "rank": 16,
        "stat": 103.4
      },
      {
        "team": "CLE",
        "rank": 17,
        "stat": 103.5
      },
      {
        "team": "LAC",
        "rank": 18,
        "stat": 104.2
      },
      {
        "team": "PHI",
        "rank": 19,
        "stat": 104.4
      },
      {
        "team": "NYK",
        "rank": 20,
        "stat": 104.6
      },
      {
        "team": "UTA",
        "rank": 21,
        "stat": 104.6
      },
      {
        "team": "POR",
        "rank": 22,
        "stat": 104.9
      },
      {
        "team": "WAS",
        "rank": 23,
        "stat": 105.6
      },
      {
        "team": "PHX",
        "rank": 24,
        "stat": 106
      },
      {
        "team": "LAL",
        "rank": 25,
        "stat": 107.2
      },
      {
        "team": "SAC",
        "rank": 26,
        "stat": 107.7
      },
      {
        "team": "HOU",
        "rank": 27,
        "stat": 108.3
      },
      {
        "team": "MIL",
        "rank": 28,
        "stat": 108.4
      },
      {
        "team": "NOP",
        "rank": 29,
        "stat": 108.6
      },
      {
        "team": "DEN",
        "rank": 30,
        "stat": 109
      }
    ]
  },
  {
    "month": 12,
    "year": 2015,
    "rankings": [
      {
        "team": "SAS",
        "rank": 1,
        "stat": 92.9
      },
      {
        "team": "CLE",
        "rank": 2,
        "stat": 98.9
      },
      {
        "team": "BOS",
        "rank": 3,
        "stat": 100.4
      },
      {
        "team": "CHI",
        "rank": 4,
        "stat": 102.1
      },
      {
        "team": "GSW",
        "rank": 5,
        "stat": 102.6
      },
      {
        "team": "OKC",
        "rank": 6,
        "stat": 102.7
      },
      {
        "team": "ORL",
        "rank": 7,
        "stat": 102.8
      },
      {
        "team": "LAC",
        "rank": 8,
        "stat": 102.8
      },
      {
        "team": "TOR",
        "rank": 9,
        "stat": 103.1
      },
      {
        "team": "CHA",
        "rank": 10,
        "stat": 103.2
      },
      {
        "team": "DET",
        "rank": 11,
        "stat": 103.4
      },
      {
        "team": "ATL",
        "rank": 12,
        "stat": 103.4
      },
      {
        "team": "IND",
        "rank": 13,
        "stat": 104.2
      },
      {
        "team": "HOU",
        "rank": 14,
        "stat": 104.2
      },
      {
        "team": "SAC",
        "rank": 15,
        "stat": 105
      },
      {
        "team": "WAS",
        "rank": 16,
        "stat": 105.5
      },
      {
        "team": "DAL",
        "rank": 17,
        "stat": 105.5
      },
      {
        "team": "NYK",
        "rank": 18,
        "stat": 105.6
      },
      {
        "team": "MIA",
        "rank": 19,
        "stat": 106.1
      },
      {
        "team": "MEM",
        "rank": 20,
        "stat": 106.2
      },
      {
        "team": "NOP",
        "rank": 21,
        "stat": 107.1
      },
      {
        "team": "MIL",
        "rank": 22,
        "stat": 107.4
      },
      {
        "team": "PHI",
        "rank": 23,
        "stat": 107.9
      },
      {
        "team": "PHX",
        "rank": 24,
        "stat": 108
      },
      {
        "team": "BKN",
        "rank": 25,
        "stat": 108
      },
      {
        "team": "MIN",
        "rank": 26,
        "stat": 108.1
      },
      {
        "team": "POR",
        "rank": 27,
        "stat": 108.1
      },
      {
        "team": "UTA",
        "rank": 28,
        "stat": 108.2
      },
      {
        "team": "DEN",
        "rank": 29,
        "stat": 109.9
      },
      {
        "team": "LAL",
        "rank": 30,
        "stat": 111
      }
    ]
  },
  {
    "month": 1,
    "year": 2016,
    "rankings": [
      {
        "team": "ATL",
        "rank": 1,
        "stat": 100.8
      },
      {
        "team": "LAC",
        "rank": 2,
        "stat": 101.7
      },
      {
        "team": "IND",
        "rank": 3,
        "stat": 101.8
      },
      {
        "team": "GSW",
        "rank": 4,
        "stat": 102.1
      },
      {
        "team": "SAS",
        "rank": 5,
        "stat": 102.3
      },
      {
        "team": "BOS",
        "rank": 6,
        "stat": 102.6
      },
      {
        "team": "MIA",
        "rank": 7,
        "stat": 102.7
      },
      {
        "team": "UTA",
        "rank": 8,
        "stat": 103.4
      },
      {
        "team": "TOR",
        "rank": 9,
        "stat": 104
      },
      {
        "team": "NOP",
        "rank": 10,
        "stat": 104.3
      },
      {
        "team": "OKC",
        "rank": 11,
        "stat": 104.9
      },
      {
        "team": "MEM",
        "rank": 12,
        "stat": 105
      },
      {
        "team": "DAL",
        "rank": 13,
        "stat": 105.3
      },
      {
        "team": "CLE",
        "rank": 14,
        "stat": 105.4
      },
      {
        "team": "CHI",
        "rank": 15,
        "stat": 106.4
      },
      {
        "team": "SAC",
        "rank": 16,
        "stat": 106.7
      },
      {
        "team": "POR",
        "rank": 17,
        "stat": 106.8
      },
      {
        "team": "CHA",
        "rank": 18,
        "stat": 106.9
      },
      {
        "team": "DET",
        "rank": 19,
        "stat": 107
      },
      {
        "team": "PHI",
        "rank": 20,
        "stat": 107.1
      },
      {
        "team": "MIL",
        "rank": 21,
        "stat": 107.8
      },
      {
        "team": "DEN",
        "rank": 22,
        "stat": 107.9
      },
      {
        "team": "LAL",
        "rank": 23,
        "stat": 108.2
      },
      {
        "team": "WAS",
        "rank": 24,
        "stat": 108.7
      },
      {
        "team": "BKN",
        "rank": 25,
        "stat": 108.9
      },
      {
        "team": "ORL",
        "rank": 26,
        "stat": 109.1
      },
      {
        "team": "NYK",
        "rank": 27,
        "stat": 109.3
      },
      {
        "team": "HOU",
        "rank": 28,
        "stat": 110.7
      },
      {
        "team": "MIN",
        "rank": 29,
        "stat": 111.1
      },
      {
        "team": "PHX",
        "rank": 30,
        "stat": 111.8
      }
    ]
  },
  {
    "month": 2,
    "year": 2016,
    "rankings": [
      {
        "team": "ATL",
        "rank": 1,
        "stat": 97.3
      },
      {
        "team": "LAC",
        "rank": 2,
        "stat": 101.2
      },
      {
        "team": "CHA",
        "rank": 3,
        "stat": 101.7
      },
      {
        "team": "SAS",
        "rank": 4,
        "stat": 101.7
      },
      {
        "team": "WAS",
        "rank": 5,
        "stat": 103
      },
      {
        "team": "POR",
        "rank": 6,
        "stat": 103.2
      },
      {
        "team": "MIA",
        "rank": 7,
        "stat": 103.6
      },
      {
        "team": "UTA",
        "rank": 8,
        "stat": 103.7
      },
      {
        "team": "MIL",
        "rank": 9,
        "stat": 104.3
      },
      {
        "team": "DEN",
        "rank": 10,
        "stat": 104.3
      },
      {
        "team": "IND",
        "rank": 11,
        "stat": 104.5
      },
      {
        "team": "BOS",
        "rank": 12,
        "stat": 105.2
      },
      {
        "team": "DET",
        "rank": 13,
        "stat": 105.3
      },
      {
        "team": "CLE",
        "rank": 14,
        "stat": 105.6
      },
      {
        "team": "GSW",
        "rank": 15,
        "stat": 106.5
      },
      {
        "team": "MEM",
        "rank": 16,
        "stat": 107.5
      },
      {
        "team": "ORL",
        "rank": 17,
        "stat": 107.5
      },
      {
        "team": "HOU",
        "rank": 18,
        "stat": 108.5
      },
      {
        "team": "NYK",
        "rank": 19,
        "stat": 109.2
      },
      {
        "team": "BKN",
        "rank": 20,
        "stat": 109.3
      },
      {
        "team": "CHI",
        "rank": 21,
        "stat": 109.4
      },
      {
        "team": "OKC",
        "rank": 22,
        "stat": 110.3
      },
      {
        "team": "NOP",
        "rank": 23,
        "stat": 110.9
      },
      {
        "team": "DAL",
        "rank": 24,
        "stat": 111.1
      },
      {
        "team": "TOR",
        "rank": 25,
        "stat": 111.7
      },
      {
        "team": "PHX",
        "rank": 26,
        "stat": 112.4
      },
      {
        "team": "SAC",
        "rank": 27,
        "stat": 113
      },
      {
        "team": "PHI",
        "rank": 28,
        "stat": 113.6
      },
      {
        "team": "LAL",
        "rank": 29,
        "stat": 116.3
      },
      {
        "team": "MIN",
        "rank": 30,
        "stat": 116.7
      }
    ]
  },
  {
    "month": 3,
    "year": 2016,
    "rankings": [
      {
        "team": "ATL",
        "rank": 1,
        "stat": 99.1
      },
      {
        "team": "SAS",
        "rank": 2,
        "stat": 99.6
      },
      {
        "team": "UTA",
        "rank": 3,
        "stat": 100.7
      },
      {
        "team": "IND",
        "rank": 4,
        "stat": 103.6
      },
      {
        "team": "WAS",
        "rank": 5,
        "stat": 103.6
      },
      {
        "team": "CHA",
        "rank": 6,
        "stat": 103.7
      },
      {
        "team": "GSW",
        "rank": 7,
        "stat": 104.1
      },
      {
        "team": "OKC",
        "rank": 8,
        "stat": 104.5
      },
      {
        "team": "NYK",
        "rank": 9,
        "stat": 106
      },
      {
        "team": "SAC",
        "rank": 10,
        "stat": 106.1
      },
      {
        "team": "CLE",
        "rank": 11,
        "stat": 106.4
      },
      {
        "team": "LAC",
        "rank": 12,
        "stat": 106.5
      },
      {
        "team": "TOR",
        "rank": 13,
        "stat": 106.7
      },
      {
        "team": "BOS",
        "rank": 14,
        "stat": 106.8
      },
      {
        "team": "HOU",
        "rank": 15,
        "stat": 106.8
      },
      {
        "team": "NOP",
        "rank": 16,
        "stat": 107.1
      },
      {
        "team": "MIA",
        "rank": 17,
        "stat": 107.3
      },
      {
        "team": "ORL",
        "rank": 18,
        "stat": 107.6
      },
      {
        "team": "MIL",
        "rank": 19,
        "stat": 108
      },
      {
        "team": "PHX",
        "rank": 20,
        "stat": 108.2
      },
      {
        "team": "CHI",
        "rank": 21,
        "stat": 108.7
      },
      {
        "team": "DET",
        "rank": 22,
        "stat": 109.1
      },
      {
        "team": "DEN",
        "rank": 23,
        "stat": 109.9
      },
      {
        "team": "POR",
        "rank": 24,
        "stat": 109.9
      },
      {
        "team": "MIN",
        "rank": 25,
        "stat": 110.1
      },
      {
        "team": "LAL",
        "rank": 26,
        "stat": 110.1
      },
      {
        "team": "MEM",
        "rank": 27,
        "stat": 110.2
      },
      {
        "team": "PHI",
        "rank": 28,
        "stat": 110.6
      },
      {
        "team": "DAL",
        "rank": 29,
        "stat": 111.2
      },
      {
        "team": "BKN",
        "rank": 30,
        "stat": 115.5
      }
    ]
  },
  {
    "month": 4,
    "year": 2016,
    "rankings": [
      {
        "team": "LAC",
        "rank": 1,
        "stat": 97.2
      },
      {
        "team": "ATL",
        "rank": 2,
        "stat": 98.6
      },
      {
        "team": "DAL",
        "rank": 3,
        "stat": 100
      },
      {
        "team": "UTA",
        "rank": 4,
        "stat": 101.4
      },
      {
        "team": "IND",
        "rank": 5,
        "stat": 102.1
      },
      {
        "team": "HOU",
        "rank": 6,
        "stat": 103
      },
      {
        "team": "PHX",
        "rank": 7,
        "stat": 103.1
      },
      {
        "team": "SAS",
        "rank": 8,
        "stat": 103.4
      },
      {
        "team": "WAS",
        "rank": 9,
        "stat": 104
      },
      {
        "team": "TOR",
        "rank": 10,
        "stat": 104.5
      },
      {
        "team": "OKC",
        "rank": 11,
        "stat": 105.1
      },
      {
        "team": "GSW",
        "rank": 12,
        "stat": 105.3
      },
      {
        "team": "BOS",
        "rank": 13,
        "stat": 105.3
      },
      {
        "team": "NYK",
        "rank": 14,
        "stat": 105.3
      },
      {
        "team": "CHA",
        "rank": 15,
        "stat": 106
      },
      {
        "team": "MIA",
        "rank": 16,
        "stat": 106.2
      },
      {
        "team": "DET",
        "rank": 17,
        "stat": 106.3
      },
      {
        "team": "CLE",
        "rank": 18,
        "stat": 106.6
      },
      {
        "team": "MIN",
        "rank": 19,
        "stat": 108.2
      },
      {
        "team": "MIL",
        "rank": 20,
        "stat": 109.1
      },
      {
        "team": "LAL",
        "rank": 21,
        "stat": 109.5
      },
      {
        "team": "PHI",
        "rank": 22,
        "stat": 109.6
      },
      {
        "team": "SAC",
        "rank": 23,
        "stat": 110
      },
      {
        "team": "POR",
        "rank": 24,
        "stat": 110.3
      },
      {
        "team": "ORL",
        "rank": 25,
        "stat": 111.3
      },
      {
        "team": "CHI",
        "rank": 26,
        "stat": 111.5
      },
      {
        "team": "DEN",
        "rank": 27,
        "stat": 111.7
      },
      {
        "team": "MEM",
        "rank": 28,
        "stat": 113.7
      },
      {
        "team": "NOP",
        "rank": 29,
        "stat": 115.4
      },
      {
        "team": "BKN",
        "rank": 30,
        "stat": 116.5
      }
    ]
  }
]