[
  {
    "month": 10,
    "year": 2006,
    "rankings": [
      {
        "team": "CHI",
        "rank": 1,
        "stat": 117.4
      },
      {
        "team": "LAL",
        "rank": 2,
        "stat": 109.6
      },
      {
        "team": "PHX",
        "rank": 3,
        "stat": 102.9
      },
      {
        "team": "MIA",
        "rank": 4,
        "stat": 71
      }
    ]
  },
  {
    "month": 11,
    "year": 2006,
    "rankings": [
      {
        "team": "GSW",
        "rank": 1,
        "stat": 109.1
      },
      {
        "team": "DET",
        "rank": 2,
        "stat": 109
      },
      {
        "team": "UTA",
        "rank": 3,
        "stat": 108.9
      },
      {
        "team": "DAL",
        "rank": 4,
        "stat": 108.4
      },
      {
        "team": "PHX",
        "rank": 5,
        "stat": 107.8
      },
      {
        "team": "DEN",
        "rank": 6,
        "stat": 107.7
      },
      {
        "team": "LAL",
        "rank": 7,
        "stat": 107.5
      },
      {
        "team": "SEA",
        "rank": 8,
        "stat": 106.4
      },
      {
        "team": "SAS",
        "rank": 9,
        "stat": 105.6
      },
      {
        "team": "CLE",
        "rank": 10,
        "stat": 104.9
      },
      {
        "team": "MIL",
        "rank": 11,
        "stat": 104.9
      },
      {
        "team": "BOS",
        "rank": 12,
        "stat": 104.9
      },
      {
        "team": "SAC",
        "rank": 13,
        "stat": 104.8
      },
      {
        "team": "POR",
        "rank": 14,
        "stat": 104.5
      },
      {
        "team": "ORL",
        "rank": 15,
        "stat": 104.1
      },
      {
        "team": "WAS",
        "rank": 16,
        "stat": 103.9
      },
      {
        "team": "PHI",
        "rank": 17,
        "stat": 103.4
      },
      {
        "team": "NYK",
        "rank": 18,
        "stat": 102.9
      },
      {
        "team": "LOS",
        "rank": 19,
        "stat": 102.7
      },
      {
        "team": "TOR",
        "rank": 20,
        "stat": 102.7
      },
      {
        "team": "ATL",
        "rank": 21,
        "stat": 102.3
      },
      {
        "team": "NJN",
        "rank": 22,
        "stat": 102.3
      },
      {
        "team": "HOU",
        "rank": 23,
        "stat": 101.8
      },
      {
        "team": "MEM",
        "rank": 24,
        "stat": 100.9
      },
      {
        "team": "MIA",
        "rank": 25,
        "stat": 100.9
      },
      {
        "team": "MIN",
        "rank": 26,
        "stat": 100.8
      },
      {
        "team": "CHI",
        "rank": 27,
        "stat": 100.6
      },
      {
        "team": "IND",
        "rank": 28,
        "stat": 100.5
      },
      {
        "team": "NOK",
        "rank": 29,
        "stat": 100.2
      },
      {
        "team": "CHA",
        "rank": 30,
        "stat": 95.9
      }
    ]
  },
  {
    "month": 12,
    "year": 2006,
    "rankings": [
      {
        "team": "WAS",
        "rank": 1,
        "stat": 117.2
      },
      {
        "team": "PHX",
        "rank": 2,
        "stat": 115.1
      },
      {
        "team": "SAS",
        "rank": 3,
        "stat": 114.3
      },
      {
        "team": "MIL",
        "rank": 4,
        "stat": 114
      },
      {
        "team": "CHI",
        "rank": 5,
        "stat": 108.8
      },
      {
        "team": "LAL",
        "rank": 6,
        "stat": 107.9
      },
      {
        "team": "DET",
        "rank": 7,
        "stat": 107.4
      },
      {
        "team": "UTA",
        "rank": 8,
        "stat": 107.1
      },
      {
        "team": "DAL",
        "rank": 9,
        "stat": 106.3
      },
      {
        "team": "DEN",
        "rank": 10,
        "stat": 106.3
      },
      {
        "team": "GSW",
        "rank": 11,
        "stat": 105.1
      },
      {
        "team": "BOS",
        "rank": 12,
        "stat": 104.5
      },
      {
        "team": "SAC",
        "rank": 13,
        "stat": 104.5
      },
      {
        "team": "MEM",
        "rank": 14,
        "stat": 104.4
      },
      {
        "team": "NJN",
        "rank": 15,
        "stat": 104.3
      },
      {
        "team": "NYK",
        "rank": 16,
        "stat": 104.1
      },
      {
        "team": "LOS",
        "rank": 17,
        "stat": 104
      },
      {
        "team": "POR",
        "rank": 18,
        "stat": 103.7
      },
      {
        "team": "SEA",
        "rank": 19,
        "stat": 103.4
      },
      {
        "team": "HOU",
        "rank": 20,
        "stat": 102.8
      },
      {
        "team": "CLE",
        "rank": 21,
        "stat": 102.5
      },
      {
        "team": "IND",
        "rank": 22,
        "stat": 102.1
      },
      {
        "team": "MIA",
        "rank": 23,
        "stat": 102.1
      },
      {
        "team": "MIN",
        "rank": 24,
        "stat": 102.1
      },
      {
        "team": "TOR",
        "rank": 25,
        "stat": 101.8
      },
      {
        "team": "ORL",
        "rank": 26,
        "stat": 101.2
      },
      {
        "team": "PHI",
        "rank": 27,
        "stat": 101
      },
      {
        "team": "CHA",
        "rank": 28,
        "stat": 100.3
      },
      {
        "team": "NOK",
        "rank": 29,
        "stat": 97.9
      },
      {
        "team": "ATL",
        "rank": 30,
        "stat": 97.6
      }
    ]
  },
  {
    "month": 1,
    "year": 2007,
    "rankings": [
      {
        "team": "PHX",
        "rank": 1,
        "stat": 116.8
      },
      {
        "team": "DAL",
        "rank": 2,
        "stat": 114.7
      },
      {
        "team": "WAS",
        "rank": 3,
        "stat": 111.4
      },
      {
        "team": "MEM",
        "rank": 4,
        "stat": 110.5
      },
      {
        "team": "NYK",
        "rank": 5,
        "stat": 109.8
      },
      {
        "team": "UTA",
        "rank": 6,
        "stat": 109.8
      },
      {
        "team": "LAL",
        "rank": 7,
        "stat": 108.3
      },
      {
        "team": "MIA",
        "rank": 8,
        "stat": 108.1
      },
      {
        "team": "MIN",
        "rank": 9,
        "stat": 108
      },
      {
        "team": "HOU",
        "rank": 10,
        "stat": 107.9
      },
      {
        "team": "SEA",
        "rank": 11,
        "stat": 107.6
      },
      {
        "team": "TOR",
        "rank": 12,
        "stat": 107.4
      },
      {
        "team": "CHA",
        "rank": 13,
        "stat": 106.9
      },
      {
        "team": "DET",
        "rank": 14,
        "stat": 106.6
      },
      {
        "team": "NJN",
        "rank": 15,
        "stat": 105.9
      },
      {
        "team": "SAC",
        "rank": 16,
        "stat": 105.9
      },
      {
        "team": "IND",
        "rank": 17,
        "stat": 105.7
      },
      {
        "team": "DEN",
        "rank": 18,
        "stat": 104.8
      },
      {
        "team": "LOS",
        "rank": 19,
        "stat": 104.8
      },
      {
        "team": "CLE",
        "rank": 20,
        "stat": 104.6
      },
      {
        "team": "SAS",
        "rank": 21,
        "stat": 104.3
      },
      {
        "team": "PHI",
        "rank": 22,
        "stat": 102.8
      },
      {
        "team": "GSW",
        "rank": 23,
        "stat": 102.8
      },
      {
        "team": "ORL",
        "rank": 24,
        "stat": 102.8
      },
      {
        "team": "POR",
        "rank": 25,
        "stat": 102.2
      },
      {
        "team": "ATL",
        "rank": 26,
        "stat": 102
      },
      {
        "team": "NOK",
        "rank": 27,
        "stat": 101
      },
      {
        "team": "CHI",
        "rank": 28,
        "stat": 99.8
      },
      {
        "team": "BOS",
        "rank": 29,
        "stat": 99.5
      },
      {
        "team": "MIL",
        "rank": 30,
        "stat": 98.3
      }
    ]
  },
  {
    "month": 2,
    "year": 2007,
    "rankings": [
      {
        "team": "TOR",
        "rank": 1,
        "stat": 114.2
      },
      {
        "team": "UTA",
        "rank": 2,
        "stat": 112.3
      },
      {
        "team": "DAL",
        "rank": 3,
        "stat": 111.1
      },
      {
        "team": "PHX",
        "rank": 4,
        "stat": 111
      },
      {
        "team": "SAS",
        "rank": 5,
        "stat": 110
      },
      {
        "team": "DET",
        "rank": 6,
        "stat": 109.3
      },
      {
        "team": "MIA",
        "rank": 7,
        "stat": 108.4
      },
      {
        "team": "LAL",
        "rank": 8,
        "stat": 107.3
      },
      {
        "team": "NOK",
        "rank": 9,
        "stat": 107.2
      },
      {
        "team": "MIL",
        "rank": 10,
        "stat": 107
      },
      {
        "team": "NYK",
        "rank": 11,
        "stat": 106.8
      },
      {
        "team": "ORL",
        "rank": 12,
        "stat": 106.7
      },
      {
        "team": "SEA",
        "rank": 13,
        "stat": 106.1
      },
      {
        "team": "NJN",
        "rank": 14,
        "stat": 105.9
      },
      {
        "team": "DEN",
        "rank": 15,
        "stat": 105.6
      },
      {
        "team": "ATL",
        "rank": 16,
        "stat": 104.8
      },
      {
        "team": "POR",
        "rank": 17,
        "stat": 104.7
      },
      {
        "team": "MEM",
        "rank": 18,
        "stat": 103.8
      },
      {
        "team": "SAC",
        "rank": 19,
        "stat": 103.3
      },
      {
        "team": "IND",
        "rank": 20,
        "stat": 103.3
      },
      {
        "team": "CHI",
        "rank": 21,
        "stat": 103.2
      },
      {
        "team": "BOS",
        "rank": 22,
        "stat": 102.8
      },
      {
        "team": "WAS",
        "rank": 23,
        "stat": 102.6
      },
      {
        "team": "CLE",
        "rank": 24,
        "stat": 102.6
      },
      {
        "team": "HOU",
        "rank": 25,
        "stat": 101.9
      },
      {
        "team": "GSW",
        "rank": 26,
        "stat": 101.1
      },
      {
        "team": "LOS",
        "rank": 27,
        "stat": 100.8
      },
      {
        "team": "MIN",
        "rank": 28,
        "stat": 100.6
      },
      {
        "team": "CHA",
        "rank": 29,
        "stat": 99.7
      },
      {
        "team": "PHI",
        "rank": 30,
        "stat": 99.2
      }
    ]
  },
  {
    "month": 3,
    "year": 2007,
    "rankings": [
      {
        "team": "DAL",
        "rank": 1,
        "stat": 112.6
      },
      {
        "team": "PHX",
        "rank": 2,
        "stat": 112.3
      },
      {
        "team": "WAS",
        "rank": 3,
        "stat": 109.2
      },
      {
        "team": "SAS",
        "rank": 4,
        "stat": 109
      },
      {
        "team": "NOK",
        "rank": 5,
        "stat": 108.3
      },
      {
        "team": "DET",
        "rank": 6,
        "stat": 107.6
      },
      {
        "team": "SEA",
        "rank": 7,
        "stat": 106.6
      },
      {
        "team": "GSW",
        "rank": 8,
        "stat": 106.6
      },
      {
        "team": "HOU",
        "rank": 9,
        "stat": 106.3
      },
      {
        "team": "CHA",
        "rank": 10,
        "stat": 106.1
      },
      {
        "team": "CLE",
        "rank": 11,
        "stat": 106
      },
      {
        "team": "DEN",
        "rank": 12,
        "stat": 105.7
      },
      {
        "team": "POR",
        "rank": 13,
        "stat": 105.6
      },
      {
        "team": "UTA",
        "rank": 14,
        "stat": 105.6
      },
      {
        "team": "MEM",
        "rank": 15,
        "stat": 105.2
      },
      {
        "team": "MIL",
        "rank": 16,
        "stat": 104.7
      },
      {
        "team": "CHI",
        "rank": 17,
        "stat": 103.9
      },
      {
        "team": "LOS",
        "rank": 18,
        "stat": 103.7
      },
      {
        "team": "TOR",
        "rank": 19,
        "stat": 103.3
      },
      {
        "team": "MIA",
        "rank": 20,
        "stat": 103.3
      },
      {
        "team": "SAC",
        "rank": 21,
        "stat": 103
      },
      {
        "team": "LAL",
        "rank": 22,
        "stat": 102.6
      },
      {
        "team": "NJN",
        "rank": 23,
        "stat": 102
      },
      {
        "team": "PHI",
        "rank": 24,
        "stat": 101.9
      },
      {
        "team": "NYK",
        "rank": 25,
        "stat": 101.6
      },
      {
        "team": "ATL",
        "rank": 26,
        "stat": 101.1
      },
      {
        "team": "BOS",
        "rank": 27,
        "stat": 100.4
      },
      {
        "team": "ORL",
        "rank": 28,
        "stat": 100.4
      },
      {
        "team": "MIN",
        "rank": 29,
        "stat": 99.9
      },
      {
        "team": "IND",
        "rank": 30,
        "stat": 95
      }
    ]
  },
  {
    "month": 4,
    "year": 2007,
    "rankings": [
      {
        "team": "GSW",
        "rank": 1,
        "stat": 115.1
      },
      {
        "team": "PHX",
        "rank": 2,
        "stat": 114.9
      },
      {
        "team": "ORL",
        "rank": 3,
        "stat": 113.4
      },
      {
        "team": "DEN",
        "rank": 4,
        "stat": 111.7
      },
      {
        "team": "MEM",
        "rank": 5,
        "stat": 111.2
      },
      {
        "team": "LAL",
        "rank": 6,
        "stat": 110.8
      },
      {
        "team": "NOK",
        "rank": 7,
        "stat": 110.8
      },
      {
        "team": "SAC",
        "rank": 8,
        "stat": 110.2
      },
      {
        "team": "SAS",
        "rank": 9,
        "stat": 109.9
      },
      {
        "team": "UTA",
        "rank": 10,
        "stat": 109.3
      },
      {
        "team": "HOU",
        "rank": 11,
        "stat": 108.6
      },
      {
        "team": "IND",
        "rank": 12,
        "stat": 108.1
      },
      {
        "team": "LOS",
        "rank": 13,
        "stat": 107.8
      },
      {
        "team": "CHA",
        "rank": 14,
        "stat": 107.6
      },
      {
        "team": "TOR",
        "rank": 15,
        "stat": 107.4
      },
      {
        "team": "CHI",
        "rank": 16,
        "stat": 107.1
      },
      {
        "team": "PHI",
        "rank": 17,
        "stat": 106.9
      },
      {
        "team": "ATL",
        "rank": 18,
        "stat": 106.3
      },
      {
        "team": "CLE",
        "rank": 19,
        "stat": 105.8
      },
      {
        "team": "SEA",
        "rank": 20,
        "stat": 105.7
      },
      {
        "team": "MIL",
        "rank": 21,
        "stat": 105.7
      },
      {
        "team": "NJN",
        "rank": 22,
        "stat": 105.3
      },
      {
        "team": "DET",
        "rank": 23,
        "stat": 103.6
      },
      {
        "team": "WAS",
        "rank": 24,
        "stat": 103.5
      },
      {
        "team": "DAL",
        "rank": 25,
        "stat": 103.3
      },
      {
        "team": "BOS",
        "rank": 26,
        "stat": 102.1
      },
      {
        "team": "MIN",
        "rank": 27,
        "stat": 102
      },
      {
        "team": "POR",
        "rank": 28,
        "stat": 101.8
      },
      {
        "team": "NYK",
        "rank": 29,
        "stat": 99.8
      },
      {
        "team": "MIA",
        "rank": 30,
        "stat": 99.3
      }
    ]
  }
]